tulipplugins/__init__.py
tulip_python-6.0.0.dist-info/RECORD
tulip_python-6.0.0.dist-info/WHEEL
tulip_python-6.0.0.dist-info/top_level.txt
tulip_python-6.0.0.dist-info/METADATA
tulip/__init__.py
tulip/native/libtulip-core-6.0.dylib
tulip/native/_tulip.cpython-39-darwin.so
tulip/native/sip.cpython-39-darwin.so
tulip/native/plugins/libSpanningDagSelection-6.0.0.dylib
tulip/native/plugins/libTreeReingoldAndTilforExtended-6.0.0.dylib
tulip/native/plugins/libWangRong-6.0.0.dylib
tulip/native/plugins/libERImport-6.0.0.dylib
tulip/native/plugins/libEmptyGraph-6.0.0.dylib
tulip/native/plugins/libLiuEtAl-6.0.0.dylib
tulip/native/plugins/libQuotientClustering-6.0.0.dylib
tulip/native/plugins/libCliqueEnumeration-6.0.0.dylib
tulip/native/plugins/libSmallWorldGraph-6.0.0.dylib
tulip/native/plugins/libEdgeSeparation-6.0.0.dylib
tulip/native/plugins/libInducedSubGraphSelection-6.0.0.dylib
tulip/native/plugins/libConnectedComponent-6.0.0.dylib
tulip/native/plugins/libGMLImport-6.0.0.dylib
tulip/native/plugins/libCompleteGraph-6.0.0.dylib
tulip/native/plugins/libNeighborhoodMetric-6.0.0.dylib
tulip/native/plugins/libGrid-6.0.0.dylib
tulip/native/plugins/libPlanarGraph-6.0.0.dylib
tulip/native/plugins/libKCores-6.0.0.dylib
tulip/native/plugins/libBibTeXImport-6.0.0.dylib
tulip/native/plugins/libCantazaro-6.0.0.dylib
tulip/native/plugins/libTree-6.0.0.dylib
tulip/native/plugins/libDepthMetric-6.0.0.dylib
tulip/native/plugins/libNodeMetric-6.0.0.dylib
tulip/native/plugins/libBiconnected-6.0.0.dylib
tulip/native/plugins/libSimple-6.0.0.dylib
tulip/native/plugins/libFastOverlapRemoval-6.0.0.dylib
tulip/native/plugins/libLinLog-6.0.0.dylib
tulip/native/plugins/libConnected-6.0.0.dylib
tulip/native/plugins/libPolyominoPacking-6.0.0.dylib
tulip/native/plugins/libImportUCINET-6.0.0.dylib
tulip/native/plugins/libWattsStrotgatz-6.0.0.dylib
tulip/native/plugins/libImportPajek-6.0.0.dylib
tulip/native/plugins/libTriconnected-6.0.0.dylib
tulip/native/plugins/libHierarchicalClustering-6.0.0.dylib
tulip/native/plugins/libPlanarity-6.0.0.dylib
tulip/native/plugins/libHolmeKim-6.0.0.dylib
